pgaspect/__init__.py
pgaspect/aspectwindow.py
pgaspect-0.0.1.dist-info/LICENSE
pgaspect-0.0.1.dist-info/METADATA
pgaspect-0.0.1.dist-info/WHEEL
pgaspect-0.0.1.dist-info/top_level.txt
pgaspect-0.0.1.dist-info/RECORD
