Metadata-Version: 2.1
Name: pgaspect
Version: 0.0.1
Summary: Resizable window with target aspect ratio
Author: Sphere (Michael Williams)
Author-email: <michaelwilliamscoding@gmail.com>
Keywords: python,pygame,window,game
Classifier: Development Status :: 1 - Planning
Classifier: Intended Audience :: Developers
Classifier: Programming Language :: Python :: 3
Classifier: Operating System :: Unix
Classifier: Operating System :: MacOS :: MacOS X
Classifier: Operating System :: Microsoft :: Windows
License-File: LICENSE
Requires-Dist: pygame
